onion_network/__init__.py
onion_network/generation.py
onion_network/visualization.py
onion_network-1.0.2.dist-info/LICENSE
onion_network-1.0.2.dist-info/METADATA
onion_network-1.0.2.dist-info/WHEEL
onion_network-1.0.2.dist-info/top_level.txt
onion_network-1.0.2.dist-info/RECORD
