Metadata-Version: 2.1
Name: onion-network
Version: 1.0.2
Summary: A module for generating and visualizing onion-structured networks!
Home-page: https://github.com/SimonPop/onion_network
Author: Simon Popelier
Author-email: simon.popelier@gmail.com
License-File: LICENSE
Requires-Dist: matplotlib (==3.7.1)
Requires-Dist: networkx (==3.1)
